sen/__init__.py
sen/cli.py
sen/constants.py
sen/docker_backend.py
sen/exceptions.py
sen/net.py
sen/util.py
sen/tui/__init__.py
sen/tui/buffer.py
sen/tui/constants.py
sen/tui/init.py
sen/tui/ui.py
sen/tui/chunks/__init__.py
sen/tui/chunks/container.py
sen/tui/chunks/image.py
sen/tui/chunks/misc.py
sen/tui/commands/__init__.py
sen/tui/commands/backend.py
sen/tui/commands/base.py
sen/tui/commands/display.py
sen/tui/commands/ui.py
sen/tui/commands/widget.py
sen/tui/views/__init__.py
sen/tui/views/base.py
sen/tui/views/container_info.py
sen/tui/views/disk_usage.py
sen/tui/views/help.py
sen/tui/views/image_info.py
sen/tui/views/main.py
sen/tui/widgets/__init__.py
sen/tui/widgets/graph.py
sen/tui/widgets/responsive_column.py
sen/tui/widgets/table.py
sen/tui/widgets/tree.py
sen/tui/widgets/util.py
sen/tui/widgets/list/__init__.py
sen/tui/widgets/list/base.py
sen/tui/widgets/list/common.py
sen/tui/widgets/list/util.py
sen-0.8.1.dist-info/licenses/LICENSE
sen-0.8.1.dist-info/METADATA
sen-0.8.1.dist-info/WHEEL
sen-0.8.1.dist-info/entry_points.txt
sen-0.8.1.dist-info/top_level.txt
sen-0.8.1.dist-info/RECORD
