Metadata-Version: 2.4
Name: sen
Version: 0.8.1
Summary: Terminal User Interface for Docker and Podman
Author-email: Tomas Tomecek <tomas@tomecek.net>
License: MIT
Project-URL: Homepage, https://github.com/TomasTomecek/sen/
Project-URL: Repository, https://github.com/TomasTomecek/sen/
Classifier: Development Status :: 5 - Production/Stable
Classifier: Intended Audience :: Developers
Classifier: Intended Audience :: System Administrators
Classifier: License :: OSI Approved :: MIT License
Classifier: Operating System :: POSIX :: Linux
Classifier: Programming Language :: Python :: Implementation :: CPython
Classifier: Programming Language :: Python :: 3
Classifier: Programming Language :: Python :: 3 :: Only
Classifier: Topic :: System :: Monitoring
Requires-Python: >=3.4
License-File: LICENSE
Requires-Dist: urwid
Requires-Dist: docker
Requires-Dist: urwidtrees
Dynamic: license-file
